.gitattributes
.gitignore
.travis.yml
LICENSE
MANIFEST.in
README.md
environment.txt
setup.cfg
setup.py
versioneer.py
data/__init__.py
data/data_directory.txt
scepia/__init__.py
scepia/_version.py
scepia/cli.py
scepia/data.py
scepia/plot.py
scepia/sc.py
scepia/util.py
scepia.egg-info/PKG-INFO
scepia.egg-info/SOURCES.txt
scepia.egg-info/dependency_links.txt
scepia.egg-info/entry_points.txt
scepia.egg-info/not-zip-safe
scepia.egg-info/requires.txt
scepia.egg-info/top_level.txt
scripts/scepia
tests/test_1_basics.py
tutorials/scepia_tutorial.ipynb