Metadata-Version: 2.1
Name: scepia
Version: 0.5.0
Summary: Inference of transcription factor motif activity from single cell RNA-seq data.
Home-page: https://github.com/vanheeringen-lab/scepia/
Author: Simon van Heeringen
Author-email: simon.vanheeringen@gmail.com
License: MIT
Platform: UNKNOWN
Classifier: Development Status :: 4 - Beta
Classifier: Intended Audience :: Science/Research
Classifier: License :: OSI Approved :: MIT License
Classifier: Operating System :: MacOS :: MacOS X
Classifier: Operating System :: POSIX :: Linux
Classifier: Programming Language :: Python :: 3.6
Classifier: Programming Language :: Python :: 3.7
Classifier: Programming Language :: Python :: 3.8
Classifier: Programming Language :: Python :: 3
Classifier: Topic :: Scientific/Engineering :: Bio-Informatics
